pynlfff/__init__.py
pynlfff/cnlfff/__init__.py
pynlfff/pycheck/__init__.py
pynlfff/pycheck/rcheck.py
pynlfff/pycomputer/__init__.py
pynlfff/pycomputer/cpu/__init__.py
pynlfff/pycomputer/cpu/run_group.py
pynlfff/pycomputer/cpu/run_one.py
pynlfff/pydownload/__init__.py
pynlfff/pydownload/download_deepsolar.py
pynlfff/pydownload/download_jsoc.py
pynlfff/pylabel/__init__.py
pynlfff/pylabel/create_label.py
pynlfff/pyplot/__init__.py
pynlfff/pyplot/plot2d_gif.py
pynlfff/pyplot/plot3d_body.py
pynlfff/pyplot/plot3d_cut.py
pynlfff/pyprepare/__init__.py
pynlfff/pyprepare/check_grid123.py
pynlfff/pyprepare/disambiguation.py
pynlfff/pyprepare/prepare_base.py
pynlfff/pyprepare/prepare_group.py
pynlfff/pyprepare/prepare_one.py
pynlfff/pyproduct/__init__.py
pynlfff/pyproduct/file.py
pynlfff/pyproduct/quality.py
pynlfff-0.3.3.5.dist-info/METADATA
pynlfff-0.3.3.5.dist-info/WHEEL
pynlfff-0.3.3.5.dist-info/top_level.txt
pynlfff-0.3.3.5.dist-info/RECORD
