Metadata-Version: 2.1
Name: pynlfff
Version: 0.3.3.5
Summary: python for nlfff
Home-page: https://github.com/deepsolar/pynlfff
Author: ZhongRui Zhao, Xinze Zhang
Author-email: zhaozhongrui21@mails.ucas.ac.cn
License: MIT
Keywords: python nlfff
Platform: UNKNOWN
Requires-Python: >=3
Requires-Dist: numpy
Requires-Dist: h5py
Requires-Dist: matplotlib
